fat_llama_fftw/__init__.py
fat_llama_fftw/audio_fattener/__init__.py
fat_llama_fftw/audio_fattener/feed.py
fat_llama_fftw/tests/__init__.py
fat_llama_fftw/tests/test_feed.py
fat_llama_fftw-1.0.4.4.dist-info/LICENSE
fat_llama_fftw-1.0.4.4.dist-info/METADATA
fat_llama_fftw-1.0.4.4.dist-info/WHEEL
fat_llama_fftw-1.0.4.4.dist-info/entry_points.txt
fat_llama_fftw-1.0.4.4.dist-info/top_level.txt
fat_llama_fftw-1.0.4.4.dist-info/RECORD
