Metadata-Version: 2.1
Name: fat_llama_fftw
Version: 1.0.4.4
Summary: fat_llama_fftw is a Python package for upscaling audio files to FLAC or WAV formats using advanced audio processing techniques. It utilizes cpu-accelerated calculations to enhance audio quality by upsampling and adding missing frequencies through FFT (Fast Fourier Transform), resulting in richer and more detailed audio.
Home-page: https://github.com/bkraad47/fat_llama_fftw
Author: RaAd
Author-email: bulkguy47@gmail.com
License: BSD-3-Clause
Classifier: Development Status :: 5 - Production/Stable
Classifier: Intended Audience :: Developers
Classifier: License :: OSI Approved :: BSD License
Classifier: Programming Language :: Python :: 3.9
Classifier: Programming Language :: Python :: 3.10
Classifier: Programming Language :: Python :: 3.11
Classifier: Programming Language :: Python :: 3.12
License-File: LICENSE
Requires-Dist: numpy
Requires-Dist: pyfftw
Requires-Dist: pydub
Requires-Dist: soundfile
Requires-Dist: mutagen
Requires-Dist: scipy
